TikTokAPI/__init__.py
TikTokAPI/tiktok_browser.py
TikTokAPI/tiktokapi.py
TikTokAPI/utils.py
TikTokAPI/website/acrawler.js
TikTokAPI/website/acrawler_raw.js
TikTokAPI/website/tiktok.html
PTTAPI-0.0.5.dist-info/LICENSE
PTTAPI-0.0.5.dist-info/METADATA
PTTAPI-0.0.5.dist-info/WHEEL
PTTAPI-0.0.5.dist-info/top_level.txt
PTTAPI-0.0.5.dist-info/RECORD
