Metadata-Version: 2.1
Name: PTTAPI
Version: 0.0.5
Summary: Unofficial TikTok API wrapper in Python with Async
Home-page: https://github.com/aswiro/PTTAPI
Download-URL: https://github.com/aswiro/PTTAPI
Author: Avilash Kumar/aswiro
Author-email: areff.hirad@gmail.com
License: MIT
Keywords: tiktok,python,api,tiktok-api,tiktok api
Classifier: Programming Language :: Python :: 3
Classifier: License :: OSI Approved :: MIT License
Classifier: Operating System :: OS Independent
Classifier: Intended Audience :: Developers
Classifier: Topic :: Software Development :: Build Tools
License-File: LICENSE
Requires-Dist: requests
Requires-Dist: pyppeteer
Requires-Dist: pyppeteer-stealth
